{
  "url": "api/qualityprofiles/search",
  "dependencies": [],
  "paginationKey": null,
  "resultKeys": [
    "profiles"
  ],
  "parameters": {},
  "operations": [],
  "mappings": [
    {
      "destination": "profile",
      "source": "$",
      "uniqueKeys": [
        "profile_key"
      ],
      "columns": [
        {
          "path": "$.key",
          "name": "profile_key"
        },
        {
          "path": "$.name",
          "name": "name"
        },
        {
          "path": "$.language",
          "name": "language"
        },
        {
          "path": "$.isInherited",
          "name": "is_inherited"
        },
        {
          "path": "$.isDefault",
          "name": "is_default"
        },
        {
          "path": "$.isBuiltIn",
          "name": "is_built_in"
        },
        {
          "path": "$.rulesUpdatedAt",
          "name": "rules_updated_ts",
          "operations": [
            {
              "operator": "convert_to_timestamp"
            }
          ]
        },
        {
          "path": "$.lastUsed",
          "name": "last_used_ts",
          "operations": [
            {
              "operator": "convert_to_timestamp"
            }
          ]
        }
      ]
    }
  ]
}
