{
  "dependencies": [
    {
      "key": "getGates",
      "strategy": "each"
    }
  ],
  "editions": [
    "enterprise",
    "teams"
  ],
  "operations": [
    {
      "operation": "apply_filter",
      "kwargs": {
        "operator": {
          "value": {
            "raw": "eq"
          }
        },
        "left": {
          "value": {
            "source": "getGates",
            "path": "$.name"
          }
        },
        "right": {
          "value": {
            "raw": "Sonar way"
          }
        }
      }
    },
    {
      "operation": "http_request",
      "kwargs": {
        "url": {
          "value": {
            "raw": "/api/qualitygates/set_as_default"
          }
        },
        "client": {
          "value": {
            "source": "inputs",
            "path": "url"
          }
        },
        "method": {
          "value": {
            "raw": "POST"
          }
        },
        "encoding": {
          "value": {
            "raw": "x-www-form-urlencoded"
          }
        },
        "resultKey": {
          "value": {
            "raw": "$"
          }
        },
        "payload": {
          "value": {
            "map": {
              "organization": {
                "value": {
                  "source": "inputs",
                  "path": "org_key"
                }
              },
              "id": {
                "value": {
                  "source": "getGates",
                  "path": "$.id"
                }
              }
            }
          }
        }
      }
    }
  ]
}